vsmlib/__init__.py
vsmlib/__main__.py
vsmlib/_version.py
vsmlib/model.py
vsmlib/visualize.py
vsmlib/benchmarks/__init__.py
vsmlib/benchmarks/do_toefl.py
vsmlib/benchmarks/toefl.py
vsmlib/benchmarks/analogy/__init__.py
vsmlib/benchmarks/analogy/__main__.py
vsmlib/benchmarks/analogy/analogy.py
vsmlib/benchmarks/analogy/visualize.py
vsmlib/benchmarks/data/toefl/toefl.ans
vsmlib/benchmarks/data/toefl/toefl.qst
vsmlib/benchmarks/sentence_classification/__init__.py
vsmlib/benchmarks/sentence_classification/__main__.py
vsmlib/benchmarks/sentence_classification/train_cnn.py
vsmlib/benchmarks/sentence_classification/CNN/CNN.py
vsmlib/benchmarks/sentence_classification/CNN/DataProcessor.py
vsmlib/benchmarks/sentence_classification/CNN/__init__.py
vsmlib/benchmarks/sentence_classification/CNN/util.py
vsmlib/benchmarks/sequence_labeling/__init__.py
vsmlib/benchmarks/sequence_labeling/__main__.py
vsmlib/benchmarks/sequence_labeling/load_data.py
vsmlib/benchmarks/sequence_labeling/sequence_labeling.py
vsmlib/benchmarks/similarity/__init__.py
vsmlib/benchmarks/similarity/__main__.py
vsmlib/benchmarks/similarity/similarity.py
vsmlib/blas/__init__.py
vsmlib/blas/blas.py
vsmlib/blas/sparse.py
vsmlib/corpus/__init__.py
vsmlib/corpus/corpus.py
vsmlib/embeddings/__init__.py
vsmlib/embeddings/convert_hdf5_csr.py
vsmlib/embeddings/convert_hdf5_factorized.py
vsmlib/embeddings/do_svd.py
vsmlib/embeddings/do_svd_slepc.py
vsmlib/embeddings/train_word2vec.py
vsmlib/embeddings/window_iterators.py
vsmlib/embeddings/bofang/__init__.py
vsmlib/embeddings/bofang/annotate_corpus_nltk.py
vsmlib/embeddings/bofang/annotate_corpus_spacy.py
vsmlib/embeddings/bofang/subword.py
vsmlib/embeddings/bofang/train_word2vec_subword_chainer_input.py
vsmlib/embeddings/bofang/utils_subword_rnn.py
vsmlib/misc/__init__.py
vsmlib/misc/data.py
vsmlib/misc/deprecated.py
vsmlib/misc/formathelper.py
vsmlib/vocabulary/__init__.py
vsmlib/vocabulary/__main__.py
vsmlib-0.1.22.dist-info/DESCRIPTION.rst
vsmlib-0.1.22.dist-info/METADATA
vsmlib-0.1.22.dist-info/RECORD
vsmlib-0.1.22.dist-info/WHEEL
vsmlib-0.1.22.dist-info/entry_points.txt
vsmlib-0.1.22.dist-info/metadata.json
vsmlib-0.1.22.dist-info/top_level.txt
