Metadata-Version: 2.0
Name: vsmlib
Version: 0.1.22
Summary: toolbox for various tasks in the area of vector space models of computational linguistic
Home-page: http://vsm.blackbird.pw/
Author: UNKNOWN
Author-email: UNKNOWN
License: UNKNOWN
Keywords: NLP,linguistics,language
Platform: UNKNOWN
Classifier: Development Status :: 3 - Alpha
Classifier: Environment :: Console
Classifier: Intended Audience :: Science/Research
Classifier: License :: OSI Approved :: Apache Software License
Classifier: Natural Language :: English
Classifier: Operating System :: POSIX
Classifier: Programming Language :: Python :: 3.5
Classifier: Programming Language :: Python :: 3.6
Classifier: Programming Language :: Python :: 3 :: Only
Classifier: Topic :: Text Processing :: Linguistic
Requires-Dist: numpy
Requires-Dist: scipy
Requires-Dist: sklearn
Requires-Dist: matplotlib
Requires-Dist: brewer2mpl
Requires-Dist: tables
Requires-Dist: tqdm
Requires-Dist: progressbar2
Requires-Dist: pyyaml
Requires-Dist: chainer
Requires-Dist: system-query
Requires-Dist: pillow
